watermarkerer/WaterMarker.py
watermarkerer/__init__.py
Watermarkerer-0.2.dist-info/METADATA
Watermarkerer-0.2.dist-info/WHEEL
Watermarkerer-0.2.dist-info/top_level.txt
Watermarkerer-0.2.dist-info/RECORD
